autoit/__init__.py
autoit/autoit.py
autoit/control.py
autoit/process.py
autoit/win.py
autoit/lib/AutoItX3.dll
autoit/lib/AutoItX3_x64.dll
PyAutoIt-0.6.0.dist-info/LICENSE
PyAutoIt-0.6.0.dist-info/METADATA
PyAutoIt-0.6.0.dist-info/WHEEL
PyAutoIt-0.6.0.dist-info/top_level.txt
PyAutoIt-0.6.0.dist-info/RECORD
