Metadata-Version: 1.1
Name: PyAutoIt
Version: 0.6.0
Summary: Python binding for AutoItX3.dll
Home-page: https://github.com/jacexh/pyautoit
Author: Jace Xu
Author-email: jace.xh@gmail.com
License: MIT
Platform: UNKNOWN
Classifier: Development Status :: 5 - Production/Stable
Classifier: Environment :: Win32 (MS Windows)
Classifier: Intended Audience :: Developers
Classifier: License :: OSI Approved :: MIT License
Classifier: Operating System :: Microsoft :: Windows
Classifier: Programming Language :: Python
Classifier: Topic :: Software Development :: Testing
